opq/__init__.py
opq/clocked.py
opq/handler.py
opq/objects.py
opq/persist.py
opq/threads.py
opq/modules/__init__.py
opq/modules/cmd.py
opq/modules/flt.py
opq/modules/irc.py
opq/modules/log.py
opq/modules/rss.py
opq/modules/sts.py
opq/modules/tdo.py
opq/modules/thr.py
opq/modules/upt.py
opq/modules/utility.py
opq-15.data/scripts/opq
opq-15.data/scripts/opqc
opq-15.data/scripts/opqd
opq-15.dist-info/METADATA
opq-15.dist-info/WHEEL
opq-15.dist-info/top_level.txt
opq-15.dist-info/zip-safe
opq-15.dist-info/RECORD
