Metadata-Version: 2.1
Name: opq
Version: 15
Summary: functional programming with objects
Home-page: http://github.com/operbot/opq
Author: Bart Thate
Author-email: operbot100@gmail.com
License: Public Domain
Platform: UNKNOWN
Classifier: Development Status :: 4 - Beta
Classifier: License :: Public Domain
Classifier: Programming Language :: Python :: 3 :: Only
Classifier: Topic :: Software Development :: Libraries :: Python Modules
